popup/__init__.py
popup/admin.py
popup/apps.py
popup/models.py
popup/static/popup/css/style.css
popup/static/popup/img/BP.jpg
popup/static/popup/img/RL.jpg
popup/static/popup/img/RX.jpg
popup/static/popup/img/WP.jpg
popup/static/popup/img/YP.jpg
popup/static/popup/js/jquery-3.6.0.min.js
popup/static/popup/js/jquery.cookie.js
popup/templates/popup/event.html
popup/templates/popup/image.html
popup/templates/popup/noti.html
popup/templates/popup/popup.html
popup/templatetags/__init__.py
popup/templatetags/popup_tags.py
django_popup_ds-0.0.3.dist-info/LICENSE
django_popup_ds-0.0.3.dist-info/METADATA
django_popup_ds-0.0.3.dist-info/WHEEL
django_popup_ds-0.0.3.dist-info/top_level.txt
django_popup_ds-0.0.3.dist-info/RECORD
